{
	"color": {
		"base": {
			"blue": {
				"50": { "value": "#f0f4ff" },
				"100": { "value": "#e0e7ff" },
				"200": { "value": "#c7d2fe" },
				"300": { "value": "#a5b4fc" },
				"400": { "value": "#818cf8" },
				"500": { "value": "#6366f1" },
				"600": { "value": "#4f46e5" },
				"700": { "value": "#4338ca" },
				"800": { "value": "#3730a3" },
				"900": { "value": "#312e81" }
			},
			"indigo": {
				"50": { "value": "#eef2ff" },
				"100": { "value": "#e0e7ff" },
				"200": { "value": "#c7d2fe" },
				"300": { "value": "#a5b4fc" },
				"400": { "value": "#818cf8" },
				"500": { "value": "#6366f1" },
				"600": { "value": "#4f46e5" },
				"700": { "value": "#4338ca" },
				"800": { "value": "#3730a3" },
				"900": { "value": "#312e81" }
			},
			"slate": {
				"50": { "value": "#f8fafc" },
				"100": { "value": "#f1f5f9" },
				"200": { "value": "#e2e8f0" },
				"300": { "value": "#cbd5e1" },
				"400": { "value": "#94a3b8" },
				"500": { "value": "#64748b" },
				"600": { "value": "#475569" },
				"700": { "value": "#334155" },
				"800": { "value": "#1e293b" },
				"900": { "value": "#0f172a" }
			},
			"gray": {
				"50": { "value": "#f9fafb" },
				"100": { "value": "#f3f4f6" },
				"200": { "value": "#e5e7eb" },
				"300": { "value": "#d1d5db" },
				"400": { "value": "#9ca3af" },
				"500": { "value": "#6b7280" },
				"600": { "value": "#4b5563" },
				"700": { "value": "#374151" },
				"800": { "value": "#1f2937" },
				"900": { "value": "#111827" }
			},
			"green": {
				"50": { "value": "#f0fdf4" },
				"100": { "value": "#dcfce7" },
				"200": { "value": "#bbf7d0" },
				"300": { "value": "#86efac" },
				"400": { "value": "#4ade80" },
				"500": { "value": "#22c55e" },
				"600": { "value": "#16a34a" },
				"700": { "value": "#15803d" },
				"800": { "value": "#166534" },
				"900": { "value": "#14532d" }
			},
			"emerald": {
				"50": { "value": "#ecfdf5" },
				"100": { "value": "#d1fae5" },
				"200": { "value": "#a7f3d0" },
				"300": { "value": "#6ee7b7" },
				"400": { "value": "#34d399" },
				"500": { "value": "#10b981" },
				"600": { "value": "#059669" },
				"700": { "value": "#047857" },
				"800": { "value": "#065f46" },
				"900": { "value": "#064e3b" }
			},
			"amber": {
				"50": { "value": "#fffbeb" },
				"100": { "value": "#fef3c7" },
				"200": { "value": "#fde68a" },
				"300": { "value": "#fcd34d" },
				"400": { "value": "#fbbf24" },
				"500": { "value": "#f59e0b" },
				"600": { "value": "#d97706" },
				"700": { "value": "#b45309" },
				"800": { "value": "#92400e" },
				"900": { "value": "#78350f" }
			},
			"orange": {
				"50": { "value": "#fff7ed" },
				"100": { "value": "#ffedd5" },
				"200": { "value": "#fed7aa" },
				"300": { "value": "#fdba74" },
				"400": { "value": "#fb923c" },
				"500": { "value": "#f97316" },
				"600": { "value": "#ea580c" },
				"700": { "value": "#c2410c" },
				"800": { "value": "#9a3412" },
				"900": { "value": "#7c2d12" }
			},
			"red": {
				"50": { "value": "#fef2f2" },
				"100": { "value": "#fee2e2" },
				"200": { "value": "#fecaca" },
				"300": { "value": "#fca5a5" },
				"400": { "value": "#f87171" },
				"500": { "value": "#ef4444" },
				"600": { "value": "#dc2626" },
				"700": { "value": "#b91c1c" },
				"800": { "value": "#991b1b" },
				"900": { "value": "#7f1d1d" }
			},
			"rose": {
				"50": { "value": "#fff1f2" },
				"100": { "value": "#ffe4e6" },
				"200": { "value": "#fecdd3" },
				"300": { "value": "#fda4af" },
				"400": { "value": "#fb7185" },
				"500": { "value": "#f43f5e" },
				"600": { "value": "#e11d48" },
				"700": { "value": "#be123c" },
				"800": { "value": "#9f1239" },
				"900": { "value": "#881337" }
			},
			"purple": {
				"50": { "value": "#faf5ff" },
				"100": { "value": "#f3e8ff" },
				"200": { "value": "#e9d5ff" },
				"300": { "value": "#d8b4fe" },
				"400": { "value": "#c084fc" },
				"500": { "value": "#a855f7" },
				"600": { "value": "#9333ea" },
				"700": { "value": "#7c3aed" },
				"800": { "value": "#6b21a8" },
				"900": { "value": "#581c87" }
			},
			"violet": {
				"50": { "value": "#f5f3ff" },
				"100": { "value": "#ede9fe" },
				"200": { "value": "#ddd6fe" },
				"300": { "value": "#c4b5fd" },
				"400": { "value": "#a78bfa" },
				"500": { "value": "#8b5cf6" },
				"600": { "value": "#7c3aed" },
				"700": { "value": "#6d28d9" },
				"800": { "value": "#5b21b6" },
				"900": { "value": "#4c1d95" }
			},
			"cyan": {
				"50": { "value": "#ecfeff" },
				"100": { "value": "#cffafe" },
				"200": { "value": "#a5f3fc" },
				"300": { "value": "#67e8f9" },
				"400": { "value": "#22d3ee" },
				"500": { "value": "#06b6d4" },
				"600": { "value": "#0891b2" },
				"700": { "value": "#0e7490" },
				"800": { "value": "#155e75" },
				"900": { "value": "#164e63" }
			},
			"teal": {
				"50": { "value": "#f0fdfa" },
				"100": { "value": "#ccfbf1" },
				"200": { "value": "#99f6e4" },
				"300": { "value": "#5eead4" },
				"400": { "value": "#2dd4bf" },
				"500": { "value": "#14b8a6" },
				"600": { "value": "#0d9488" },
				"700": { "value": "#0f766e" },
				"800": { "value": "#115e59" },
				"900": { "value": "#134e4a" }
			}
		},
		"semantic": {
			"brand": {
				"primary": { "value": "{color.base.blue.600}", "comment": "Primary brand color" },
				"primary-hover": { "value": "{color.base.blue.700}", "comment": "Primary color on hover" },
				"primary-light": { "value": "{color.base.blue.50}", "comment": "Light primary background" },
				"secondary": { "value": "{color.base.slate.600}", "comment": "Secondary brand color" },
				"secondary-hover": { "value": "{color.base.slate.700}", "comment": "Secondary color on hover" },
				"accent": { "value": "{color.base.indigo.500}", "comment": "Accent color" },
				"accent-hover": { "value": "{color.base.indigo.600}", "comment": "Accent color on hover" }
			},

			"status": {
				"success": { "value": "{color.base.emerald.600}", "comment": "Success state" },
				"success-hover": { "value": "{color.base.emerald.700}", "comment": "Success state on hover" },
				"success-light": { "value": "{color.base.emerald.50}", "comment": "Light success background" },
				"warning": { "value": "{color.base.amber.500}", "comment": "Warning state" },
				"warning-hover": { "value": "{color.base.amber.600}", "comment": "Warning state on hover" },
				"warning-light": { "value": "{color.base.amber.50}", "comment": "Light warning background" },
				"error": { "value": "{color.base.red.600}", "comment": "Error state" },
				"error-hover": { "value": "{color.base.red.700}", "comment": "Error state on hover" },
				"error-light": { "value": "{color.base.red.50}", "comment": "Light error background" },
				"info": { "value": "{color.base.cyan.600}", "comment": "Info state" },
				"info-hover": { "value": "{color.base.cyan.700}", "comment": "Info state on hover" },
				"info-light": { "value": "{color.base.cyan.50}", "comment": "Light info background" }
			},

			"background": {
				"primary": { "value": "#ffffff", "comment": "Main background" },
				"secondary": { "value": "{color.base.slate.50}", "comment": "Secondary background" },
				"tertiary": { "value": "{color.base.slate.100}", "comment": "Tertiary background" },
				"elevated": { "value": "#ffffff", "comment": "Elevated surface background" },
				"overlay": { "value": "rgba(0, 0, 0, 0.5)", "comment": "Overlay background" }
			},

			"surface": {
				"card": { "value": "#ffffff", "comment": "Card surface" },
				"card-hover": { "value": "{color.base.slate.50}", "comment": "Card surface on hover" },
				"modal": { "value": "#ffffff", "comment": "Modal surface" },
				"dropdown": { "value": "#ffffff", "comment": "Dropdown surface" },
				"tooltip": { "value": "{color.base.slate.800}", "comment": "Tooltip surface" }
			},

			"text": {
				"primary": { "value": "{color.base.slate.900}", "comment": "Primary text color" },
				"secondary": { "value": "{color.base.slate.600}", "comment": "Secondary text color" },
				"tertiary": { "value": "{color.base.slate.500}", "comment": "Tertiary text color" },
				"disabled": { "value": "{color.base.slate.400}", "comment": "Disabled text color" },
				"inverse": { "value": "#ffffff", "comment": "Inverse text color" },
				"on-primary": { "value": "#ffffff", "comment": "Text on primary background" },
				"on-secondary": { "value": "#ffffff", "comment": "Text on secondary background" },
				"on-success": { "value": "#ffffff", "comment": "Text on success background" },
				"on-warning": { "value": "{color.base.slate.900}", "comment": "Text on warning background" },
				"on-error": { "value": "#ffffff", "comment": "Text on error background" },
				"on-info": { "value": "#ffffff", "comment": "Text on info background" }
			},

			"interactive": {
				"button": {
					"primary": { "value": "{color.base.blue.600}", "comment": "Primary button background" },
					"primary-hover": { "value": "{color.base.blue.700}", "comment": "Primary button hover" },
					"primary-active": { "value": "{color.base.blue.800}", "comment": "Primary button active" },
					"secondary": { "value": "{color.base.slate.100}", "comment": "Secondary button background" },
					"secondary-hover": { "value": "{color.base.slate.200}", "comment": "Secondary button hover" },
					"secondary-active": { "value": "{color.base.slate.300}", "comment": "Secondary button active" },
					"outline": { "value": "transparent", "comment": "Outline button background" },
					"outline-hover": { "value": "{color.base.slate.50}", "comment": "Outline button hover" },
					"ghost": { "value": "transparent", "comment": "Ghost button background" },
					"ghost-hover": { "value": "{color.base.slate.100}", "comment": "Ghost button hover" },
					"text": { "value": "{color.base.slate.600}", "comment": "Button text color" },
					"text-hover": { "value": "{color.base.slate.700}", "comment": "Button text hover" },
					"text-primary": { "value": "#ffffff", "comment": "Primary button text" },
					"disabled": { "value": "{color.base.slate.300}", "comment": "Disabled button background" },
					"disabled-text": { "value": "{color.base.slate.400}", "comment": "Disabled button text" }
				},
				"link": {
					"default": { "value": "{color.base.blue.600}", "comment": "Default link color" },
					"hover": { "value": "{color.base.blue.700}", "comment": "Link hover color" },
					"active": { "value": "{color.base.blue.800}", "comment": "Link active color" },
					"visited": { "value": "{color.base.purple.600}", "comment": "Visited link color" },
					"disabled": { "value": "{color.base.slate.400}", "comment": "Disabled link color" }
				},
				"input": {
					"background": { "value": "#ffffff", "comment": "Input background" },
					"background-disabled": { "value": "{color.base.slate.50}", "comment": "Disabled input background" },
					"border": { "value": "{color.base.slate.300}", "comment": "Input border" },
					"border-hover": { "value": "{color.base.slate.400}", "comment": "Input border hover" },
					"border-focus": { "value": "{color.base.blue.500}", "comment": "Input border focus" },
					"border-error": { "value": "{color.base.red.500}", "comment": "Input border error" },
					"placeholder": { "value": "{color.base.slate.400}", "comment": "Input placeholder" }
				}
			},

			"border": {
				"default": { "value": "{color.base.slate.200}", "comment": "Default border" },
				"light": { "value": "{color.base.slate.100}", "comment": "Light border" },
				"medium": { "value": "{color.base.slate.300}", "comment": "Medium border" },
				"strong": { "value": "{color.base.slate.400}", "comment": "Strong border" },
				"focus": { "value": "{color.base.blue.500}", "comment": "Focus border" },
				"error": { "value": "{color.base.red.500}", "comment": "Error border" },
				"success": { "value": "{color.base.emerald.500}", "comment": "Success border" },
				"warning": { "value": "{color.base.amber.500}", "comment": "Warning border" },
				"divider": { "value": "{color.base.slate.200}", "comment": "Divider border" }
			},

			"shadow": {
				"sm": { "value": "0 1px 2px 0 rgba(0, 0, 0, 0.05)", "comment": "Small shadow" },
				"md": {
					"value": "0 4px 6px -1px rgba(0, 0, 0, 0.1), 0 2px 4px -1px rgba(0, 0, 0, 0.06)",
					"comment": "Medium shadow"
				},
				"lg": {
					"value": "0 10px 15px -3px rgba(0, 0, 0, 0.1), 0 4px 6px -2px rgba(0, 0, 0, 0.05)",
					"comment": "Large shadow"
				},
				"xl": {
					"value": "0 20px 25px -5px rgba(0, 0, 0, 0.1), 0 10px 10px -5px rgba(0, 0, 0, 0.04)",
					"comment": "Extra large shadow"
				},
				"inner": { "value": "inset 0 2px 4px 0 rgba(0, 0, 0, 0.06)", "comment": "Inner shadow" }
			},

			"gradient": {
				"primary": {
					"value": "linear-gradient(135deg, {color.base.blue.500} 0%, {color.base.indigo.600} 50%, {color.base.purple.600} 100%)",
					"comment": "Primary gradient"
				},
				"secondary": {
					"value": "linear-gradient(135deg, {color.base.slate.600} 0%, {color.base.gray.600} 100%)",
					"comment": "Secondary gradient"
				},
				"success": {
					"value": "linear-gradient(135deg, {color.base.emerald.500} 0%, {color.base.teal.500} 100%)",
					"comment": "Success gradient"
				},
				"warning": {
					"value": "linear-gradient(135deg, {color.base.amber.500} 0%, {color.base.orange.500} 100%)",
					"comment": "Warning gradient"
				},
				"error": {
					"value": "linear-gradient(135deg, {color.base.red.500} 0%, {color.base.rose.500} 100%)",
					"comment": "Error gradient"
				}
			},

			"utility": {
				"focus-ring": { "value": "{color.base.blue.500}", "comment": "Focus ring color" },
				"selection": { "value": "{color.base.blue.100}", "comment": "Text selection background" },
				"highlight": { "value": "{color.base.amber.100}", "comment": "Highlight background" },
				"disabled": { "value": "{color.base.slate.300}", "comment": "Disabled element color" },
				"loading": { "value": "{color.base.slate.400}", "comment": "Loading state color" }
			}
		}
	}
}
